GPTContext/__init__.py
GPTContext/ai.py
GPTContext/schema.py
gpt_contexts-0.0.7.dist-info/METADATA
gpt_contexts-0.0.7.dist-info/WHEEL
gpt_contexts-0.0.7.dist-info/licenses/LICENSE
gpt_contexts-0.0.7.dist-info/RECORD
